kiwi_mlutils/__init__.py
kiwi_mlutils/misc.py
kiwi_mlutils/perceptron.py
kiwi_mlutils/plotting.py
kiwi_mlutils/retrieval.py
kiwi_mlutils/train_loop.py
kiwi_mlutils-0.2.0.dist-info/LICENSE.md
kiwi_mlutils-0.2.0.dist-info/METADATA
kiwi_mlutils-0.2.0.dist-info/NOTICE.md
kiwi_mlutils-0.2.0.dist-info/WHEEL
kiwi_mlutils-0.2.0.dist-info/RECORD
